precios_sniim.py
SNIIMAPP_2-0.2.2.dist-info/LICENSE
SNIIMAPP_2-0.2.2.dist-info/METADATA
SNIIMAPP_2-0.2.2.dist-info/WHEEL
SNIIMAPP_2-0.2.2.dist-info/top_level.txt
SNIIMAPP_2-0.2.2.dist-info/RECORD
